wisedata/__init__.py
wisedata/exceptions.py
wisedata-1.0.13.dist-info/LICENSE
wisedata-1.0.13.dist-info/METADATA
wisedata-1.0.13.dist-info/WHEEL
wisedata-1.0.13.dist-info/RECORD
